easyxrd/__init__.py
easyxrd/core.py
easyxrd/plotters.py
easyxrd-0.1.4.dist-info/licenses/LICENSE
easyxrd-0.1.4.dist-info/METADATA
easyxrd-0.1.4.dist-info/WHEEL
easyxrd-0.1.4.dist-info/top_level.txt
easyxrd-0.1.4.dist-info/RECORD
