Metadata-Version: 2.4
Name: easyxrd
Version: 0.1.4
Summary: X-ray diffractioan analysis tool
Home-page: https://github.com/MehmetTopsakal/easyXRD
Author: Mehmet Topsakal
Author-email: metokal@gmail.com
License: GNU
Platform: any
Classifier: Development Status :: 4 - Beta
Classifier: Intended Audience :: Science/Research
Classifier: Operating System :: OS Independent
Classifier: Programming Language :: Python :: 3 :: Only
Classifier: Programming Language :: Python :: 3.11
Requires-Python: >=3.11
License-File: LICENSE
Dynamic: author
Dynamic: author-email
Dynamic: classifier
Dynamic: home-page
Dynamic: license
Dynamic: license-file
Dynamic: platform
Dynamic: requires-python
Dynamic: summary
